Combinational/MagComp_4b/min_max.v
module min_max(
    input [3:0] A,B,
    output A_less_B, A_great_B, A_equal_B
);

assign A_equal_B = (A==B)?1'b1:1'b0;
assign A_less_B = (A<B)?1'b1:1'b0;
assign A_great_B = (A>B)?1'b1:1'b0;

endmodule

Combinational/MagComp_4b/min_max_tb.v
`include "min_max.v"
`timescale 1ns/1ns

module min_max_tb;
reg [3:0] A,B;
wire A_less_B, A_great_B, A_equal_B;

min_max UUT(
    .A(A),.B(B),.A_less_B(A_less_B), .A_great_B(A_great_B), .A_equal_B(A_equal_B)
);

initial begin
    $dumpfile("min_max_tb.vcd");  // for waveform
    $dumpvars(0, min_max_tb);
    $monitor("A = %d, B = %d, A_equal_B = %b, A_great_B = %b, A_less_B = %b",A,B,A_equal_B,A_great_B,A_less_B);

    repeat(10) begin
        A = $random %16;
        B = $random %16;
        #10;
    end
    $finish;
end

endmodule

Combinational/MagComp_4b/min_max_tb.vcd
$date
	Sun Sep 28 11:16:39 2025
$end
$version
	Icarus Verilog
$end
$timescale
	1ns
$end
$scope module min_max_tb $end
$var wire 1 ! A_less_B $end
$var wire 1 " A_great_B $end
$var wire 1 # A_equal_B $end
$var reg 4 $ A [3:0] $end
$var reg 4 % B [3:0] $end
$scope module UUT $end
$var wire 4 & A [3:0] $end
$var wire 4 ' B [3:0] $end
$var wire 1 ! A_less_B $end
$var wire 1 " A_great_B $end
$var wire 1 # A_equal_B $end
$upscope $end
$upscope $end
$enddefinitions $end
$comment Show the parameter values. $end
$dumpall
$end
#0
$dumpvars
b1 '
b100 &
b1 %
b100 $
0#
1"
0!
$end
#10
b11 %
b11 '
b1001 $
b1001 &
#20
1#
0"
b1101 %
b1101 '
b1101 $
b1101 &
#30
1"
0#
b10 %
b10 '
b101 $
b101 &
#40
1!
0"
b1101 %
b1101 '
b1 $
b1 &
#50
b110 $
b110 &
#60
1"
0!
b1100 %
b1100 '
b1101 $
b1101 &
#70
b110 %
b110 '
b1001 $
b1001 &
#80
1!
0"
b1010 %
b1010 '
b101 $
b101 &
#90
b111 %
b111 '
