Sequential/WatchdogTimer/wdt.v
module wdt(
    input clock,reset,kick,
    output reg wdt_reset
);
reg [5:0] counter;
localparam PERIOD = 30;

always @(posedge clock or negedge reset) begin
    if(~reset) begin
        counter <= PERIOD;
        wdt_reset <= 0;
    end
    else begin
        if (kick) begin
            counter <= PERIOD;
            wdt_reset <= 0;
        end else if (counter > 0) begin
            counter--;
        end else begin
            wdt_reset <= 1;
        end
    end
end
endmodule

/*Watchdog Timer Logic
1. Initialization
On reset, the watchdog counter is loaded with a fixed value (TIMEOUT).
This value represents how many clock cycles the system has before the WDT expires.
2. Counting Down
On every clock edge (posedge clk), the counter decrements by 1 if it is enabled.
This is like a ticking countdown timer.
3. Kick (Feed the Dog)
The processor or main logic must periodically assert the kick signal.
When kick = 1:
The counter reloads back to the full TIMEOUT value.
This prevents the watchdog from expiring.
If the system is healthy, it should always provide kicks before the counter runs out.
4. Timeout Detection
If the counter reaches 0 and no kick occurred → the watchdog times out.
When timeout happens, the wdt_reset signal goes HIGH.
This can be connected to:
Reset the CPU/system.
Trigger a fail-safe mechanism.
5. Cycle Repeats
After a timeout, system resets → counter reloads → counting begins again.

⚡ Logical Flow (Step-by-step)
Reset signal → counter = TIMEOUT.
Clock ticks → counter = counter − 1.
If kick occurs before timeout → counter = TIMEOUT again.
If no kick and counter = 0 → wdt_reset = 1.
System responds (usually resets).*/

Sequential/WatchdogTimer/wdt_tb.v
`timescale 1ns/1ns
`include "wdt.v"

module wdt_tb;
reg clock, reset, kick;
wire wdt_reset;
wdt WDT(clock, reset, kick, wdt_reset);

initial begin
    clock = 0;
    forever #5 clock = ~clock; //10ns clock period
end
initial begin
    $dumpfile("wdt_tb.vcd");
    $dumpvars(0,wdt_tb);
    reset = 0;
    kick = 0;
    #10; reset=1;
    #10;
    // Let the counter run without kick to see timeout
    kick = 0;
    $display("Waiting for timeout...");
    #400;  // enough time for counter to reach 0
    // Now feed the watchdog (kick) before timeout
    $display("Feeding the watchdog...");
    kick = 1;
    #10 kick = 0;
    // Let it run again without kick
    #400;
    $finish; 
end
endmodule

Sequential/WatchdogTimer/wdt_tb.vcd
$date
	Fri Oct 03 13:25:31 2025
$end
$version
	Icarus Verilog
$end
$timescale
	1ns
$end
$scope module wdt_tb $end
$var wire 1 ! wdt_reset $end
$var reg 1 " clock $end
$var reg 1 # kick $end
$var reg 1 $ reset $end
$scope module WDT $end
$var wire 1 " clock $end
$var wire 1 # kick $end
$var wire 1 $ reset $end
$var parameter 32 % PERIOD $end
$var reg 6 & counter [5:0] $end
$var reg 1 ! wdt_reset $end
$upscope $end
$upscope $end
$enddefinitions $end
$comment Show the parameter values. $end
$dumpall
b11110 %
$end
#0
$dumpvars
b11110 &
0$
0#
0"
0!
$end
#5
1"
#10
0"
1$
#15
b11101 &
1"
#20
0"
#25
b11100 &
1"
#30
0"
#35
b11011 &
1"
#40
0"
#45
b11010 &
1"
#50
0"
#55
b11001 &
1"
#60
0"
#65
b11000 &
1"
#70
0"
#75
b10111 &
1"
#80
0"
#85
b10110 &
1"
#90
0"
#95
b10101 &
1"
#100
0"
#105
b10100 &
1"
#110
0"
#115
b10011 &
1"
#120
0"
#125
b10010 &
1"
#130
0"
#135
b10001 &
1"
#140
0"
#145
b10000 &
1"
#150
0"
#155
b1111 &
1"
#160
0"
#165
b1110 &
1"
#170
0"
#175
b1101 &
1"
#180
0"
#185
b1100 &
1"
#190
0"
#195
b1011 &
1"
#200
0"
#205
b1010 &
1"
#210
0"
#215
b1001 &
1"
#220
0"
#225
b1000 &
1"
#230
0"
#235
b111 &
1"
#240
0"
#245
b110 &
1"
#250
0"
#255
b101 &
1"
#260
0"
#265
b100 &
1"
#270
0"
#275
b11 &
1"
#280
0"
#285
b10 &
1"
#290
0"
#295
b1 &
1"
#300
0"
#305
b0 &
1"
#310
0"
#315
1!
1"
#320
0"
#325
1"
#330
0"
#335
1"
#340
0"
#345
1"
#350
0"
#355
1"
#360
0"
#365
1"
#370
0"
#375
1"
#380
0"
#385
1"
#390
0"
#395
1"
#400
0"
#405
1"
#410
0"
#415
1"
#420
0"
1#
#425
0!
b11110 &
1"
#430
0"
0#
#435
b11101 &
1"
#440
0"
#445
b11100 &
1"
#450
0"
#455
b11011 &
1"
#460
0"
#465
b11010 &
1"
#470
0"
#475
b11001 &
1"
#480
0"
#485
b11000 &
1"
#490
0"
#495
b10111 &
1"
#500
0"
#505
b10110 &
1"
#510
0"
#515
b10101 &
1"
#520
0"
#525
b10100 &
1"
#530
0"
#535
b10011 &
1"
#540
0"
#545
b10010 &
1"
#550
0"
#555
b10001 &
1"
#560
0"
#565
b10000 &
1"
#570
0"
#575
b1111 &
1"
#580
0"
#585
b1110 &
1"
#590
0"
#595
b1101 &
1"
#600
0"
#605
b1100 &
1"
#610
0"
#615
b1011 &
1"
#620
0"
#625
b1010 &
1"
#630
0"
#635
b1001 &
1"
#640
0"
#645
b1000 &
1"
#650
0"
#655
b111 &
1"
#660
0"
#665
b110 &
1"
#670
0"
#675
b101 &
1"
#680
0"
#685
b100 &
1"
#690
0"
#695
b11 &
1"
#700
0"
#705
b10 &
1"
#710
0"
#715
b1 &
1"
#720
0"
#725
b0 &
1"
#730
0"
#735
1!
1"
