FSM/sequence_counter_0110/sequence_counter_0110.v
module sequence_counter_0110(
    input clk, reset, din,
    output reg dout
);
// State encoding as parameters
localparam  S0 = 3'b000, // Initial state
            S1 = 3'b001, // Detected '0'
            S2 = 3'b010, // Detected '01'
            S3 = 3'b011, // Detected '011'
            S4 = 3'b100; // Detected '0110'

reg [2:0] current_state, next_state;

always @(posedge clk or posedge reset) begin
    if (reset)
        current_state <= S0; // Reset to initial state
    else
        current_state <= next_state;
end
always @(*) begin
    next_state = current_state;
    dout = 1'b0;
    case (current_state)
        S0: if (din == 1'b0) next_state = S1; // Transition to S1 on '0'
        S1: if (din == 1'b1) next_state = S2; // Transition to S2 on '1'
            else next_state = S1;            // Stay in S1 on '0'
        S2: if (din == 1'b1) next_state = S3; // Transition to S3 on '1'
            else next_state = S0;            // Back to S0 on '0'
        S3: if (din == 1'b0) next_state = S4; // Transition to S4 on '0'
            else next_state = S2;            // Back to S2 on '1'
        S4: begin
            dout = 1'b1;                 // Sequence detected
            if (din == 1'b0) next_state = S1; // Allow overlapping detection
            else next_state = S2;
        end
        default: next_state = S0;            // Default state
    endcase
end
endmodule

FSM/sequence_counter_0110/sequence_counter_0110_tb.v
`timescale 1ns/1ns
`include "sequence_counter_0110.v"

module sequence_counter_0110_tb;
    reg clk, reset, din;
    wire dout;
    sequence_counter_0110 DUT (.clk(clk), .reset(reset), .din(din), .dout(dout));

    initial begin
        clk = 0;
        forever #5 clk = ~clk;
    end

    initial begin
        $dumpfile("sequence_counter_0110.vcd");
        $dumpvars(0, sequence_counter_0110_tb);

        reset = 1;
        din = 0;

        @(posedge clk);
        reset = 0;

        // Sequence: 0110
        @(posedge clk) din = 0;  
        @(posedge clk) din = 1;  
        @(posedge clk) din = 1;  
        @(posedge clk) din = 0;  // <-- here dout will become 1

        @(posedge clk) din = 0;
        @(posedge clk) din = 0;
        @(posedge clk) din = 1;
        @(posedge clk) din = 1;
        @(posedge clk) din = 1;
        @(posedge clk) din = 0;

        #20 $finish;
    end

    initial begin
        $monitor("Time=%0t | din=%b | dout=%b", $time, din, dout);
    end

endmodule

FSM/sequence_counter_0110/sequence_counter_0110.vcd
$date
	Thu Dec 04 18:23:36 2025
$end
$version
	Icarus Verilog
$end
$timescale
	1ns
$end
$scope module sequence_counter_0110_tb $end
$var wire 1 ! dout $end
$var reg 1 " clk $end
$var reg 1 # din $end
$var reg 1 $ reset $end
$scope module DUT $end
$var wire 1 " clk $end
$var wire 1 # din $end
$var wire 1 $ reset $end
$var parameter 3 % S0 $end
$var parameter 3 & S1 $end
$var parameter 3 ' S2 $end
$var parameter 3 ( S3 $end
$var parameter 3 ) S4 $end
$var reg 3 * current_state [2:0] $end
$var reg 1 ! dout $end
$var reg 3 + next_state [2:0] $end
$upscope $end
$upscope $end
$enddefinitions $end
$comment Show the parameter values. $end
$dumpall
b100 )
b11 (
b10 '
b1 &
b0 %
$end
#0
$dumpvars
b1 +
b0 *
1$
0#
0"
0!
$end
#5
b1 *
0$
1"
#10
0"
#15
1"
#20
0"
#25
b10 +
1#
1"
#30
0"
#35
b11 +
b10 *
1"
#40
0"
#45
b11 *
b100 +
0#
1"
#50
0"
#55
b1 +
1!
b100 *
1"
#60
0"
#65
0!
b1 *
1"
#70
0"
#75
b10 +
1#
1"
#80
0"
#85
b11 +
b10 *
1"
#90
0"
#95
b10 +
b11 *
1"
#100
0"
#105
b10 *
b0 +
0#
1"
#110
0"
#115
b1 +
b0 *
1"
#120
0"
#125
b1 *
1"
