FSM/Two_seq_detector/two_seq_det.v
module two_seq_det(
    input clk, reset,
    input din,
    output reg detected_0110, detected_0111
);
localparam   IDLE = 3'b000,
               S0 = 3'b001,
              S01 = 3'b010,
             S011 = 3'b011;

reg [2:0] current_state, next_state;

always @(posedge clk or posedge reset) begin
    if (reset) current_state <= IDLE;
    else current_state <= next_state;
end

always @(*) begin
    next_state = current_state;
    detected_0110 = 1'b0;
    detected_0111 = 1'b0;
    case(current_state)
        IDLE: if (din == 1'b0) next_state = S0;
            else next_state  = IDLE;
        S0: if (din == 1'b1) next_state = S01;
            else next_state = S0;
        S01: if (din == 1'b1) next_state = S011;
            else next_state = S0;
        S011: if (din == 1'b1) begin
            next_state = IDLE;
            detected_0111 = 1;
        end
        else begin
            next_state = S0;
            detected_0110 = 1;
        end
    endcase 
end

endmodule

FSM/Two_seq_detector/two_seq_det_tb.v
`timescale 1ns/1ns
`include "two_seq_det.v"

module two_seq_det_tb;
    reg clk, reset, din;
    wire detected_0110, detected_0111;
    two_seq_det DUT (.clk(clk), .reset(reset), .din(din), .detected_0110(detected_0110), .detected_0111(detected_0111));

    initial begin
        clk = 0;
        forever #5 clk = ~clk;
    end

    initial begin
        $dumpfile("two_seq_det.vcd");
        $dumpvars(0, two_seq_det_tb);

        reset = 1;
        din = 0;

        @(posedge clk);
        reset = 0;

        // Sequence: 0110
        @(posedge clk) din = 0;  
        @(posedge clk) din = 1;  
        @(posedge clk) din = 1;  
        @(posedge clk) din = 0;  // <-- here dout will become 1

        @(posedge clk) din = 0;
        @(posedge clk) din = 0;
        @(posedge clk) din = 1;
        @(posedge clk) din = 1;
        @(posedge clk) din = 1;
        @(posedge clk) din = 0;

        #20 $finish;
    end

endmodule

FSM/Two_seq_detector/two_seq_det.vcd
$date
	Wed Dec 10 00:40:30 2025
$end
$version
	Icarus Verilog
$end
$timescale
	1ns
$end
$scope module two_seq_det_tb $end
$var wire 1 ! detected_0111 $end
$var wire 1 " detected_0110 $end
$var reg 1 # clk $end
$var reg 1 $ din $end
$var reg 1 % reset $end
$scope module DUT $end
$var wire 1 # clk $end
$var wire 1 $ din $end
$var wire 1 % reset $end
$var parameter 3 & IDLE $end
$var parameter 3 ' S0 $end
$var parameter 3 ( S01 $end
$var parameter 3 ) S011 $end
$var reg 3 * current_state [2:0] $end
$var reg 1 " detected_0110 $end
$var reg 1 ! detected_0111 $end
$var reg 3 + next_state [2:0] $end
$upscope $end
$upscope $end
$enddefinitions $end
$comment Show the parameter values. $end
$dumpall
b11 )
b10 (
b1 '
b0 &
$end
#0
$dumpvars
b1 +
b0 *
1%
0$
0#
0"
0!
$end
#5
b1 *
0%
1#
#10
0#
#15
1#
#20
0#
#25
b10 +
1$
1#
#30
0#
#35
b11 +
b10 *
1#
#40
0#
#45
1"
b11 *
b1 +
0$
1#
#50
0#
#55
0"
b1 *
1#
#60
0#
#65
1#
#70
0#
#75
b10 +
1$
1#
#80
0#
#85
b11 +
b10 *
1#
#90
0#
#95
1!
b0 +
b11 *
1#
#100
0#
#105
b0 *
0"
0!
b1 +
0$
1#
#110
0#
#115
b1 *
1#
