Sequential/freq_divider_even/freq_div_ev.v
module freq_div_ev(
    input clk, reset,
    output clk_by4
);
wire clk_by2;

d_ff d1(.D(~clk_by4), .clk(clk), .reset(reset), .Q(clk_by2));
d_ff d2(.D(clk_by2), .clk(clk), .reset(reset), .Q(clk_by4));

endmodule

module d_ff(
    input D,clk,reset,
    output reg Q
);
always @(posedge clk) begin
    if(reset) Q<= 1'b0;
    else begin
        Q = D;
    end
end
endmodule

Sequential/freq_divider_even/freq_div_ev_tb.v
`timescale 1ns/1ns
`include "freq_div_ev.v"

module freq_div_ev_tb;
reg clk, reset;
wire clk_by4;

freq_div_ev DUT (clk, reset, clk_by4);

initial begin
    clk= 1'b0;
    forever #10 clk= ~clk;
end
initial begin
    $dumpfile("freq_div_ev.vcd");
    $dumpvars(0,freq_div_ev_tb);
    reset= 1'b1;
    #20
    reset= 1'b0;
    #220 $finish;
end
endmodule

Sequential/freq_divider_even/freq_div_ev.vcd
$date
	Sun Dec 07 00:39:46 2025
$end
$version
	Icarus Verilog
$end
$timescale
	1ns
$end
$scope module freq_div_ev_tb $end
$var wire 1 ! clk_by4 $end
$var reg 1 " clk $end
$var reg 1 # reset $end
$scope module DUT $end
$var wire 1 " clk $end
$var wire 1 # reset $end
$var wire 1 ! clk_by4 $end
$var wire 1 $ clk_by2 $end
$scope module d1 $end
$var wire 1 % D $end
$var wire 1 " clk $end
$var wire 1 # reset $end
$var reg 1 $ Q $end
$upscope $end
$scope module d2 $end
$var wire 1 $ D $end
$var wire 1 " clk $end
$var wire 1 # reset $end
$var reg 1 ! Q $end
$upscope $end
$upscope $end
$upscope $end
$enddefinitions $end
$comment Show the parameter values. $end
$dumpall
$end
#0
$dumpvars
x%
x$
1#
0"
x!
$end
#10
1%
0$
0!
1"
#20
0"
0#
#30
0%
1!
1$
1"
#40
0"
#50
0$
1"
#60
0"
#70
1%
0!
1"
#80
0"
#90
1$
1"
#100
0"
#110
0%
1!
1"
#120
0"
#130
0$
1"
#140
0"
#150
1%
0!
1"
#160
0"
#170
1$
1"
#180
0"
#190
0%
1!
1"
#200
0"
#210
0$
1"
#220
0"
#230
1%
0!
1"
