Combinational/Priority_Encoder/IC_74148.v
module IC_74148(
    input  [7:0] D,   // active low inputs, D7 highest priority
    input  En,        // active low enable
    output reg [2:0] A,      // encoded output
    output reg EnOut, GS     // active low outputs
);

always @(*) begin
    if (~En) begin  // chip enabled
        casex(D)
            8'b01111111: begin A = 3'b111; GS=0; EnOut=0; end // D7=0 highest priority
            8'b10111111: begin A = 3'b110; GS=0; EnOut=0; end // D6=0
            8'b11011111: begin A = 3'b101; GS=0; EnOut=0; end // D5=0
            8'b11101111: begin A = 3'b100; GS=0; EnOut=0; end // D4=0
            8'b11110111: begin A = 3'b011; GS=0; EnOut=0; end // D3=0
            8'b11111011: begin A = 3'b010; GS=0; EnOut=0; end // D2=0
            8'b11111101: begin A = 3'b001; GS=0; EnOut=0; end // D1=0
            8'b11111110: begin A = 3'b000; GS=0; EnOut=0; end // D0=0 lowest priority
            default:     begin A = 3'b111; GS=1; EnOut=1; end // no inputs active
        endcase
    end 
    else begin        // Disabled: all outputs inactive
        A = 3'b111; GS=1; EnOut=1;
    end
end
endmodule

Combinational/Priority_Encoder/IC_74148_tb.v
`timescale 1ns/1ns
`include "IC_74148.v"

module IC_74148_tb;
reg [7:0] D;
reg En;
wire [2:0] A;
wire GS, EnOut;

IC_74148 uut (D, En, A, EnOut, GS);

initial begin
    $dumpfile("IC_74148.vcd");
    $dumpvars(0, IC_74148_tb);

    En = 0;   // enable active low

    // No input active
    D = 8'b11111111; #10;   // expect A=111, GS=1, EnOut=1

    // D0 active (lowest priority)
    D = 8'b11111110; #10;   // expect A=000, GS=0, EnOut=0

    // D1 active
    D = 8'b11111101; #10;   // expect A=001, GS=0, EnOut=0

    // D2 active
    D = 8'b11111011; #10;   // expect A=010, GS=0, EnOut=0

    // D3 active
    D = 8'b11110111; #10;   // expect A=011, GS=0, EnOut=0

    // D4 active
    D = 8'b11101111; #10;   // expect A=100, GS=0, EnOut=0

    // D5 active
    D = 8'b11011111; #10;   // expect A=101, GS=0, EnOut=0

    // D6 active
    D = 8'b10111111; #10;   // expect A=110, GS=0, EnOut=0

    // D7 active (highest priority)
    D = 8'b01111111; #10;   // expect A=111, GS=0, EnOut=0

    // Multiple inputs low (priority check)
    D = 8'b10111110; #10;   // D6 & D0 both active → D6 wins → A=110

    // Disable encoder
    En = 1; D = 8'b00000000; #10; // expect A=111, GS=1, EnOut=1

    $finish;
end

initial begin
    $monitor("time=%0t, D=%b, En=%b -> A=%b, GS=%b, EnOut=%b",
             $time, D, En, A, GS, EnOut);
end
endmodule

Combinational/Priority_Encoder/IC_74148.vcd
$date
	Thu Oct 02 16:39:51 2025
$end
$version
	Icarus Verilog
$end
$timescale
	1ns
$end
$scope module IC_74148_tb $end
$var wire 1 ! GS $end
$var wire 1 " EnOut $end
$var wire 3 # A [2:0] $end
$var reg 8 $ D [7:0] $end
$var reg 1 % En $end
$scope module uut $end
$var wire 8 & D [7:0] $end
$var wire 1 % En $end
$var reg 3 ' A [2:0] $end
$var reg 1 " EnOut $end
$var reg 1 ! GS $end
$upscope $end
$upscope $end
$enddefinitions $end
$comment Show the parameter values. $end
$dumpall
$end
#0
$dumpvars
b111 '
b11111111 &
0%
b11111111 $
b111 #
1"
1!
$end
#10
0"
0!
b0 #
b0 '
b11111110 $
b11111110 &
#20
b1 #
b1 '
b11111101 $
b11111101 &
#30
b10 #
b10 '
b11111011 $
b11111011 &
#40
b11 #
b11 '
b11110111 $
b11110111 &
#50
b100 #
b100 '
b11101111 $
b11101111 &
#60
b101 #
b101 '
b11011111 $
b11011111 &
#70
b110 #
b110 '
b10111111 $
b10111111 &
#80
b111 #
b111 '
b1111111 $
b1111111 &
#90
1"
1!
b10111110 $
b10111110 &
#100
b0 $
b0 &
1%
