DatapathBlocks/BarrelShifter/BarrelShifter.v
module BarrelShifter(
    input [7:0] data_in,
    input [2:0] shift,
    input dir, // 1 for left rotate, 0 for right rotate
    output reg [7:0] data_out
);
always @(*) begin
    if (dir)
        data_out = (data_in << shift) | (data_in >> (8 - shift));
    else
        data_out = (data_in >> shift) | (data_in << (8 - shift));
end
endmodule

DatapathBlocks/BarrelShifter/BarrelShifter_tb.v
`timescale 1ns/1ns
`include "BarrelShifter.v"
module BarrelShifter_tb;
reg [7:0] data_in;
reg [2:0] shift;
reg dir;
wire [7:0] data_out;
BarrelShifter uut(data_in, shift, dir, data_out);
initial begin
    $dumpfile("BarrelShifter.vcd");
    $dumpvars(0,BarrelShifter_tb);
end
initial begin
    data_in = 8'b11110000;
        dir = 0;
        shift = 3'b000;

        #10 shift = 3'b001; dir = 0; 
        #10 shift = 3'b010; dir = 0; 
        #10 shift = 3'b011; dir = 0; 
        #10 shift = 3'b100; dir = 1; 
        #10 shift = 3'b101; dir = 1; 
        #10 shift = 3'b110; dir = 1; 
        #10 shift = 3'b111; dir = 1;       
       
        #10 data_in = 8'b11001100; shift = 3'b001; dir = 0; 
        #10 data_in = 8'b00011111; shift = 3'b010; dir = 1; 
        #10 data_in = 8'b10101010; shift = 3'b011; dir = 0; 
        
        #10 shift = 3'b000; dir = 1;       
       
        #10 $finish;
end
initial begin
    $monitor("At time %t: data_in = %b, shift = %b, dir = %b, data_out = %b", $time, data_in, shift, dir, data_out);
end
endmodule

DatapathBlocks/BarrelShifter/BarrelShifter.vcd
$date
	Sun Oct 26 19:12:22 2025
$end
$version
	Icarus Verilog
$end
$timescale
	1ns
$end
$scope module BarrelShifter_tb $end
$var wire 8 ! data_out [7:0] $end
$var reg 8 " data_in [7:0] $end
$var reg 1 # dir $end
$var reg 3 $ shift [2:0] $end
$scope module uut $end
$var wire 8 % data_in [7:0] $end
$var wire 1 # dir $end
$var wire 3 & shift [2:0] $end
$var reg 8 ' data_out [7:0] $end
$upscope $end
$upscope $end
$enddefinitions $end
$comment Show the parameter values. $end
$dumpall
$end
#0
$dumpvars
b11110000 '
b0 &
b11110000 %
b0 $
0#
b11110000 "
b11110000 !
$end
#10
b1111000 !
b1111000 '
b1 $
b1 &
#20
b111100 !
b111100 '
b10 $
b10 &
#30
b11110 !
b11110 '
b11 $
b11 &
#40
b1111 !
b1111 '
1#
b100 $
b100 &
#50
b11110 !
b11110 '
b101 $
b101 &
#60
b111100 !
b111100 '
b110 $
b110 &
#70
b1111000 !
b1111000 '
b111 $
b111 &
#80
b1100110 !
b1100110 '
0#
b1 $
b1 &
b11001100 "
b11001100 %
#90
b1111100 !
b1111100 '
1#
b10 $
b10 &
b11111 "
b11111 %
#100
b1010101 !
b1010101 '
0#
b11 $
b11 &
b10101010 "
b10101010 %
#110
b10101010 !
b10101010 '
1#
b0 $
b0 &
